point_viz/.DS_Store
point_viz/__init__.py
point_viz/converter.py
point_viz/utils.py
point_viz/src/.DS_Store
point_viz/src/main.css
point_viz/src/template.html
point_viz/src/text_sprite.js
point_viz/src/build/d3.v4.min.js
point_viz/src/build/three.js
point_viz/src/build/three.min.js
point_viz/src/build/three.module.js
point_viz/src/jsm/controls/OrbitControls.d.ts
point_viz/src/jsm/controls/OrbitControls.js
point_viz/src/jsm/libs/dat.gui.module.js
point_viz/src/jsm/libs/stats.module.js
point_viz_test-0.0.5.dist-info/METADATA
point_viz_test-0.0.5.dist-info/RECORD
point_viz_test-0.0.5.dist-info/WHEEL
point_viz_test-0.0.5.dist-info/top_level.txt
