Metadata-Version: 2.1
Name: point-viz-test
Version: 0.0.5
Summary: A light-weight web point cloud visualizer based on Three.js
Home-page: https://github.com/SUZhaoyu/point_viz
Author: Zhaoyu Su
Author-email: zsuad@connect.ust.hk
License: UNKNOWN
Platform: UNKNOWN
Classifier: Programming Language :: Python :: 3
Classifier: License :: OSI Approved :: MIT License
Classifier: Operating System :: OS Independent
